pickupline/__init__.py
pickupline/abstract.py
pickupline/cache.py
pickupline/constants.py
pickupline/pickuplinegen.py
pickupline/pickuplinesgalore.py
pickupline-3.0.data/scripts/pickup-line
pickupline-3.0.dist-info/DESCRIPTION.rst
pickupline-3.0.dist-info/METADATA
pickupline-3.0.dist-info/RECORD
pickupline-3.0.dist-info/WHEEL
pickupline-3.0.dist-info/metadata.json
pickupline-3.0.dist-info/top_level.txt
